codebeamer/__init__.py
codebeamer/client.py
codebeamer_client-0.0.1.dist-info/METADATA
codebeamer_client-0.0.1.dist-info/WHEEL
codebeamer_client-0.0.1.dist-info/top_level.txt
codebeamer_client-0.0.1.dist-info/RECORD
